README.md
setup.py
autokeras_pretrained/__init__.py
autokeras_pretrained/base.py
autokeras_pretrained/constant.py
autokeras_pretrained/face_detector.py
autokeras_pretrained/object_detector.py
autokeras_pretrained/text_classifier.py
autokeras_pretrained/utils.py
autokeras_pretrained/voice_recognizer.py
autokeras_pretrained.egg-info/PKG-INFO
autokeras_pretrained.egg-info/SOURCES.txt
autokeras_pretrained.egg-info/dependency_links.txt
autokeras_pretrained.egg-info/requires.txt
autokeras_pretrained.egg-info/top_level.txt
autokeras_pretrained/bert/__init__.py
autokeras_pretrained/bert/modeling.py
autokeras_pretrained/bert/optimization.py
autokeras_pretrained/bert/tokenization.py
autokeras_pretrained/bert/utils.py
autokeras_pretrained/voice_generator/__init__.py
autokeras_pretrained/voice_generator/voice_generator.py
autokeras_pretrained/voice_generator/deepvoice3_pytorch/__init__.py
autokeras_pretrained/voice_generator/deepvoice3_pytorch/builder.py
autokeras_pretrained/voice_generator/deepvoice3_pytorch/conv.py
autokeras_pretrained/voice_generator/deepvoice3_pytorch/deepvoice3.py
autokeras_pretrained/voice_generator/deepvoice3_pytorch/frontend.py
autokeras_pretrained/voice_generator/deepvoice3_pytorch/model.py
autokeras_pretrained/voice_generator/deepvoice3_pytorch/modules.py
autokeras_pretrained/voice_generator/deepvoice3_pytorch/version.py
autokeras_pretrained/voice_generator/deepvoice3_pytorch/text/__init__.py
autokeras_pretrained/voice_generator/deepvoice3_pytorch/text/cleaners.py
autokeras_pretrained/voice_generator/deepvoice3_pytorch/text/cmudict.py
autokeras_pretrained/voice_generator/deepvoice3_pytorch/text/numbers.py
autokeras_pretrained/voice_generator/deepvoice3_pytorch/text/symbols.py
autokeras_pretrained/voice_generator/deepvoice3_pytorch/text/text.py
tests/pretrained/__init__.py
tests/pretrained/test_face_detector.py
tests/pretrained/test_object_detection.py
tests/pretrained/test_sentiment_analysis.py
tests/pretrained/test_topic_classifier.py
tests/pretrained/test_voice_generator.py
tests/pretrained/test_voice_recognizer.py