Metadata-Version: 1.1
Name: autokeras-pretrained
Version: 0.0.3
Summary: Pretrained models for Auto-Keras
Home-page: http://autokeras.com
Author: DATA Lab at Texas A&M University
Author-email: jhfjhfj1@gmail.com
License: UNKNOWN
Download-URL: https://github.com/jhfjhfj1/autokeras-pretrained/archive/0.0.3.tar.gz
Keywords: autokeras,keras
Platform: UNKNOWN
